{
  "sections": [
    {
      "number": 1,
      "name": "5.1 INTRODUCTION"
    },
    {
      "number": 1,
      "name": "5.1 INTRODUCTION"
    },
    {
      "number": 2,
      "name": "5.2 NOTIONS OF WORK AND KINETIC ENERGY: THE WORK-ENERGY THEOREM"
    },
    {
      "number": 2,
      "name": "5.2 NOTIONS OF WORK AND KINETIC ENERGY: THE WORK-ENERGY THEOREM"
    },
    {
      "number": 3,
      "name": "5.3 WORK"
    },
    {
      "number": 3,
      "name": "5.3 WORK"
    },
    {
      "number": 4,
      "name": "5.4 KINETIC ENERGY"
    },
    {
      "number": 4,
      "name": "5.4 KINETIC ENERGY"
    },
    {
      "number": 5,
      "name": "5.5 WORK DONE BY A VARIABLE FORCE"
    },
    {
      "number": 5,
      "name": "5.5 WORK DONE BY A VARIABLE FORCE"
    },
    {
      "number": 6,
      "name": "5.6 THE WORK-ENERGY THEOREM FOR A VARIABLE FORCE"
    },
    {
      "number": 6,
      "name": "5.6 THE WORK-ENERGY THEOREM FOR A VARIABLE FORCE"
    },
    {
      "number": 7,
      "name": "5.7 THE CONCEPT OF POTENTIAL ENERGY"
    },
    {
      "number": 7,
      "name": "5.7 THE CONCEPT OF POTENTIAL ENERGY"
    },
    {
      "number": 8,
      "name": "5.8 THE CONSERVATION OF MECHANICAL ENERGY"
    },
    {
      "number": 8,
      "name": "5.8 THE CONSERVATION OF MECHANICAL ENERGY"
    },
    {
      "number": 9,
      "name": "5.9 THE POTENTIAL ENERGY OF A SPRING"
    },
    {
      "number": 9,
      "name": "5.9 THE POTENTIAL ENERGY OF A SPRING"
    },
    {
      "number": 10,
      "name": "5.10 POWER"
    },
    {
      "number": 10,
      "name": "5.10 POWER"
    },
    {
      "number": 11,
      "name": "5.11 COLLISIONS"
    },
    {
      "number": 11,
      "name": "5.11 COLLISIONS"
    }
  ]
}